{
    "profiles": [
        {
            "complex_modifications": {
                "rules": [
                    {
                        "description": "Hyper(Shift+Option)+S -> region screenshot to clipboard",
                        "manipulators": [
                            {
                                "from": {
                                    "key_code": "s",
                                    "modifiers": {
                                        "mandatory": [
                                            "left_shift",
                                            "left_option"
                                        ]
                                    }
                                },
                                "to": [
                                    {
                                        "key_code": "4",
                                        "modifiers": [
                                            "left_command",
                                            "left_control",
                                            "left_shift"
                                        ]
                                    }
                                ],
                                "type": "basic"
                            }
                        ]
                    },
                    {
                        "description": "Shift+Esc → ~",
                        "manipulators": [
                            {
                                "from": {
                                    "key_code": "escape",
                                    "modifiers": {
                                        "mandatory": [
                                            "shift"
                                        ]
                                    }
                                },
                                "to": [
                                    {
                                        "key_code": "non_us_backslash",
                                        "modifiers": [
                                            "shift"
                                        ]
                                    }
                                ],
                                "type": "basic"
                            }
                        ]
                    },
                    {
                        "description": "Esc → `",
                        "manipulators": [
                            {
                                "from": {
                                    "key_code": "escape"
                                },
                                "to": [
                                    {
                                        "key_code": "non_us_backslash"
                                    }
                                ],
                                "type": "basic"
                            }
                        ]
                    },
                    {
                        "description": "left_control → Shift+Option",
                        "manipulators": [
                            {
                                "description": "Change left_command to left_shift + left_option.",
                                "from": {
                                    "key_code": "left_control",
                                    "modifiers": {
                                        "optional": [
                                            "any"
                                        ]
                                    }
                                },
                                "to": [
                                    {
                                        "key_code": "left_shift",
                                        "modifiers": [
                                            "left_option"
                                        ]
                                    }
                                ],
                                "type": "basic"
                            }
                        ]
                    },
                    {
                        "description": "Navigation & line editing (non-terminal)",
                        "manipulators": [
                            {
                                "conditions": [
                                    {
                                        "bundle_identifiers": [
                                            "^com\\.apple\\.Terminal$",
                                            "^com\\.googlecode\\.iterm2$",
                                            "^co\\.zeit\\.hyperterm$",
                                            "^co\\.zeit\\.hyper$",
                                            "^io\\.alacritty$",
                                            "^org\\.alacritty$",
                                            "^net\\.kovidgoyal\\.kitty$",
                                            "^com\\.microsoft\\.VSCode$"
                                        ],
                                        "type": "frontmost_application_unless"
                                    }
                                ],
                                "from": {
                                    "key_code": "h",
                                    "modifiers": {
                                        "mandatory": [
                                            "left_control"
                                        ]
                                    }
                                },
                                "to": [
                                    {
                                        "key_code": "left_arrow"
                                    }
                                ],
                                "type": "basic"
                            },
                            {
                                "conditions": [
                                    {
                                        "bundle_identifiers": [
                                            "^com\\.apple\\.Terminal$",
                                            "^com\\.googlecode\\.iterm2$",
                                            "^co\\.zeit\\.hyperterm$",
                                            "^co\\.zeit\\.hyper$",
                                            "^io\\.alacritty$",
                                            "^org\\.alacritty$",
                                            "^net\\.kovidgoyal\\.kitty$",
                                            "^com\\.microsoft\\.VSCode$"
                                        ],
                                        "type": "frontmost_application_unless"
                                    }
                                ],
                                "from": {
                                    "key_code": "j",
                                    "modifiers": {
                                        "mandatory": [
                                            "left_control"
                                        ]
                                    }
                                },
                                "to": [
                                    {
                                        "key_code": "down_arrow"
                                    }
                                ],
                                "type": "basic"
                            },
                            {
                                "conditions": [
                                    {
                                        "bundle_identifiers": [
                                            "^com\\.apple\\.Terminal$",
                                            "^com\\.googlecode\\.iterm2$",
                                            "^co\\.zeit\\.hyperterm$",
                                            "^co\\.zeit\\.hyper$",
                                            "^io\\.alacritty$",
                                            "^org\\.alacritty$",
                                            "^net\\.kovidgoyal\\.kitty$",
                                            "^com\\.microsoft\\.VSCode$"
                                        ],
                                        "type": "frontmost_application_unless"
                                    }
                                ],
                                "from": {
                                    "key_code": "k",
                                    "modifiers": {
                                        "mandatory": [
                                            "left_control"
                                        ]
                                    }
                                },
                                "to": [
                                    {
                                        "key_code": "up_arrow"
                                    }
                                ],
                                "type": "basic"
                            },
                            {
                                "conditions": [
                                    {
                                        "bundle_identifiers": [
                                            "^com\\.apple\\.Terminal$",
                                            "^com\\.googlecode\\.iterm2$",
                                            "^co\\.zeit\\.hyperterm$",
                                            "^co\\.zeit\\.hyper$",
                                            "^io\\.alacritty$",
                                            "^org\\.alacritty$",
                                            "^net\\.kovidgoyal\\.kitty$",
                                            "^com\\.microsoft\\.VSCode$"
                                        ],
                                        "type": "frontmost_application_unless"
                                    }
                                ],
                                "from": {
                                    "key_code": "l",
                                    "modifiers": {
                                        "mandatory": [
                                            "left_control"
                                        ]
                                    }
                                },
                                "to": [
                                    {
                                        "key_code": "right_arrow"
                                    }
                                ],
                                "type": "basic"
                            },
                            {
                                "conditions": [
                                    {
                                        "bundle_identifiers": [
                                            "^com\\.apple\\.Terminal$",
                                            "^com\\.googlecode\\.iterm2$",
                                            "^co\\.zeit\\.hyperterm$",
                                            "^co\\.zeit\\.hyper$",
                                            "^io\\.alacritty$",
                                            "^org\\.alacritty$",
                                            "^net\\.kovidgoyal\\.kitty$",
                                            "^com\\.microsoft\\.VSCode$"
                                        ],
                                        "type": "frontmost_application_unless"
                                    }
                                ],
                                "from": {
                                    "key_code": "b",
                                    "modifiers": {
                                        "mandatory": [
                                            "left_control"
                                        ]
                                    }
                                },
                                "to": [
                                    {
                                        "key_code": "left_arrow",
                                        "modifiers": [
                                            "option"
                                        ]
                                    }
                                ],
                                "type": "basic"
                            },
                            {
                                "conditions": [
                                    {
                                        "bundle_identifiers": [
                                            "^com\\.apple\\.Terminal$",
                                            "^com\\.googlecode\\.iterm2$",
                                            "^co\\.zeit\\.hyperterm$",
                                            "^co\\.zeit\\.hyper$",
                                            "^io\\.alacritty$",
                                            "^org\\.alacritty$",
                                            "^net\\.kovidgoyal\\.kitty$",
                                            "^com\\.microsoft\\.VSCode$"
                                        ],
                                        "type": "frontmost_application_unless"
                                    }
                                ],
                                "from": {
                                    "key_code": "f",
                                    "modifiers": {
                                        "mandatory": [
                                            "left_control"
                                        ]
                                    }
                                },
                                "to": [
                                    {
                                        "key_code": "right_arrow",
                                        "modifiers": [
                                            "option"
                                        ]
                                    }
                                ],
                                "type": "basic"
                            },
                            {
                                "conditions": [
                                    {
                                        "bundle_identifiers": [
                                            "^com\\.apple\\.Terminal$",
                                            "^com\\.googlecode\\.iterm2$",
                                            "^co\\.zeit\\.hyperterm$",
                                            "^co\\.zeit\\.hyper$",
                                            "^io\\.alacritty$",
                                            "^org\\.alacritty$",
                                            "^net\\.kovidgoyal\\.kitty$",
                                            "^com\\.microsoft\\.VSCode$"
                                        ],
                                        "type": "frontmost_application_unless"
                                    }
                                ],
                                "from": {
                                    "key_code": "w",
                                    "modifiers": {
                                        "mandatory": [
                                            "left_control"
                                        ]
                                    }
                                },
                                "to": [
                                    {
                                        "key_code": "delete_or_backspace",
                                        "modifiers": [
                                            "option"
                                        ]
                                    }
                                ],
                                "type": "basic"
                            },
                            {
                                "from": {
                                    "key_code": "d",
                                    "modifiers": {
                                        "mandatory": [
                                            "left_control"
                                        ]
                                    }
                                },
                                "to": [
                                    {
                                        "key_code": "delete_or_backspace"
                                    }
                                ],
                                "type": "basic"
                            },
                            {
                                "conditions": [
                                    {
                                        "bundle_identifiers": [
                                            "^com\\.apple\\.Terminal$",
                                            "^com\\.googlecode\\.iterm2$",
                                            "^co\\.zeit\\.hyperterm$",
                                            "^co\\.zeit\\.hyper$",
                                            "^io\\.alacritty$",
                                            "^org\\.alacritty$",
                                            "^net\\.kovidgoyal\\.kitty$",
                                            "^com\\.microsoft\\.VSCode$"
                                        ],
                                        "type": "frontmost_application_unless"
                                    }
                                ],
                                "from": {
                                    "key_code": "u",
                                    "modifiers": {
                                        "mandatory": [
                                            "left_control"
                                        ]
                                    }
                                },
                                "to": [
                                    {
                                        "key_code": "left_arrow",
                                        "modifiers": [
                                            "command",
                                            "shift"
                                        ]
                                    },
                                    {
                                        "key_code": "delete_or_backspace"
                                    }
                                ],
                                "type": "basic"
                            },
                            {
                                "conditions": [
                                    {
                                        "bundle_identifiers": [
                                            "^com\\.apple\\.Terminal$",
                                            "^com\\.googlecode\\.iterm2$",
                                            "^co\\.zeit\\.hyperterm$",
                                            "^co\\.zeit\\.hyper$",
                                            "^io\\.alacritty$",
                                            "^org\\.alacritty$",
                                            "^net\\.kovidgoyal\\.kitty$",
                                            "^com\\.microsoft\\.VSCode$"
                                        ],
                                        "type": "frontmost_application_unless"
                                    }
                                ],
                                "from": {
                                    "key_code": "v",
                                    "modifiers": {
                                        "mandatory": [
                                            "left_control"
                                        ]
                                    }
                                },
                                "to": [
                                    {
                                        "key_code": "left_arrow",
                                        "modifiers": [
                                            "option",
                                            "shift"
                                        ]
                                    }
                                ],
                                "type": "basic"
                            }
                        ]
                    },
                    {
                        "description": "Tab → Option (hold) / Tab (tap)",
                        "manipulators": [
                            {
                                "description": "Change tab to alt",
                                "from": {
                                    "key_code": "tab",
                                    "modifiers": {
                                        "optional": [
                                            "any"
                                        ]
                                    }
                                },
                                "to": [
                                    {
                                        "key_code": "left_alt"
                                    }
                                ],
                                "to_if_alone": [
                                    {
                                        "key_code": "tab"
                                    }
                                ],
                                "type": "basic"
                            }
                        ]
                    },
                    {
                        "description": "CapsLock → Control (hold) / Esc (tap)",
                        "manipulators": [
                            {
                                "description": "Change caps_lock to control",
                                "from": {
                                    "key_code": "caps_lock",
                                    "modifiers": {
                                        "optional": [
                                            "any"
                                        ]
                                    }
                                },
                                "to": [
                                    {
                                        "key_code": "left_control"
                                    }
                                ],
                                "to_if_alone": [
                                    {
                                        "key_code": "escape"
                                    }
                                ],
                                "type": "basic"
                            }
                        ]
                    }
                ]
            },
            "devices": [
                {
                    "identifiers": {
                        "is_keyboard": true,
                        "product_id": 73,
                        "vendor_id": 9610
                    },
                    "simple_modifications": [
                        {
                            "from": {
                                "key_code": "left_command"
                            },
                            "to": [
                                {
                                    "key_code": "left_option"
                                }
                            ]
                        },
                        {
                            "from": {
                                "key_code": "left_option"
                            },
                            "to": [
                                {
                                    "key_code": "left_command"
                                }
                            ]
                        }
                    ]
                }
            ],
            "name": "Default profile",
            "selected": true,
            "virtual_hid_keyboard": {
                "keyboard_type_v2": "iso"
            }
        },
        {
            "complex_modifications": {
                "rules": [
                    {
                        "description": "Navigation & line editing (non-terminal)",
                        "manipulators": [
                            {
                                "conditions": [
                                    {
                                        "bundle_identifiers": [
                                            "^com\\.apple\\.Terminal$",
                                            "^com\\.googlecode\\.iterm2$",
                                            "^co\\.zeit\\.hyperterm$",
                                            "^co\\.zeit\\.hyper$",
                                            "^io\\.alacritty$",
                                            "^org\\.alacritty$",
                                            "^net\\.kovidgoyal\\.kitty$",
                                            "^com\\.microsoft\\.VSCode$"
                                        ],
                                        "type": "frontmost_application_unless"
                                    }
                                ],
                                "from": {
                                    "key_code": "h",
                                    "modifiers": {
                                        "mandatory": [
                                            "left_control"
                                        ]
                                    }
                                },
                                "to": [
                                    {
                                        "key_code": "left_arrow"
                                    }
                                ],
                                "type": "basic"
                            },
                            {
                                "conditions": [
                                    {
                                        "bundle_identifiers": [
                                            "^com\\.apple\\.Terminal$",
                                            "^com\\.googlecode\\.iterm2$",
                                            "^co\\.zeit\\.hyperterm$",
                                            "^co\\.zeit\\.hyper$",
                                            "^io\\.alacritty$",
                                            "^org\\.alacritty$",
                                            "^net\\.kovidgoyal\\.kitty$",
                                            "^com\\.microsoft\\.VSCode$"
                                        ],
                                        "type": "frontmost_application_unless"
                                    }
                                ],
                                "from": {
                                    "key_code": "j",
                                    "modifiers": {
                                        "mandatory": [
                                            "left_control"
                                        ]
                                    }
                                },
                                "to": [
                                    {
                                        "key_code": "down_arrow"
                                    }
                                ],
                                "type": "basic"
                            },
                            {
                                "conditions": [
                                    {
                                        "bundle_identifiers": [
                                            "^com\\.apple\\.Terminal$",
                                            "^com\\.googlecode\\.iterm2$",
                                            "^co\\.zeit\\.hyperterm$",
                                            "^co\\.zeit\\.hyper$",
                                            "^io\\.alacritty$",
                                            "^org\\.alacritty$",
                                            "^net\\.kovidgoyal\\.kitty$",
                                            "^com\\.microsoft\\.VSCode$"
                                        ],
                                        "type": "frontmost_application_unless"
                                    }
                                ],
                                "from": {
                                    "key_code": "k",
                                    "modifiers": {
                                        "mandatory": [
                                            "left_control"
                                        ]
                                    }
                                },
                                "to": [
                                    {
                                        "key_code": "up_arrow"
                                    }
                                ],
                                "type": "basic"
                            },
                            {
                                "conditions": [
                                    {
                                        "bundle_identifiers": [
                                            "^com\\.apple\\.Terminal$",
                                            "^com\\.googlecode\\.iterm2$",
                                            "^co\\.zeit\\.hyperterm$",
                                            "^co\\.zeit\\.hyper$",
                                            "^io\\.alacritty$",
                                            "^org\\.alacritty$",
                                            "^net\\.kovidgoyal\\.kitty$",
                                            "^com\\.microsoft\\.VSCode$"
                                        ],
                                        "type": "frontmost_application_unless"
                                    }
                                ],
                                "from": {
                                    "key_code": "l",
                                    "modifiers": {
                                        "mandatory": [
                                            "left_control"
                                        ]
                                    }
                                },
                                "to": [
                                    {
                                        "key_code": "right_arrow"
                                    }
                                ],
                                "type": "basic"
                            },
                            {
                                "conditions": [
                                    {
                                        "bundle_identifiers": [
                                            "^com\\.apple\\.Terminal$",
                                            "^com\\.googlecode\\.iterm2$",
                                            "^co\\.zeit\\.hyperterm$",
                                            "^co\\.zeit\\.hyper$",
                                            "^io\\.alacritty$",
                                            "^org\\.alacritty$",
                                            "^net\\.kovidgoyal\\.kitty$",
                                            "^com\\.microsoft\\.VSCode$"
                                        ],
                                        "type": "frontmost_application_unless"
                                    }
                                ],
                                "from": {
                                    "key_code": "b",
                                    "modifiers": {
                                        "mandatory": [
                                            "left_control"
                                        ]
                                    }
                                },
                                "to": [
                                    {
                                        "key_code": "left_arrow",
                                        "modifiers": [
                                            "option"
                                        ]
                                    }
                                ],
                                "type": "basic"
                            },
                            {
                                "conditions": [
                                    {
                                        "bundle_identifiers": [
                                            "^com\\.apple\\.Terminal$",
                                            "^com\\.googlecode\\.iterm2$",
                                            "^co\\.zeit\\.hyperterm$",
                                            "^co\\.zeit\\.hyper$",
                                            "^io\\.alacritty$",
                                            "^org\\.alacritty$",
                                            "^net\\.kovidgoyal\\.kitty$",
                                            "^com\\.microsoft\\.VSCode$"
                                        ],
                                        "type": "frontmost_application_unless"
                                    }
                                ],
                                "from": {
                                    "key_code": "f",
                                    "modifiers": {
                                        "mandatory": [
                                            "left_control"
                                        ]
                                    }
                                },
                                "to": [
                                    {
                                        "key_code": "right_arrow",
                                        "modifiers": [
                                            "option"
                                        ]
                                    }
                                ],
                                "type": "basic"
                            },
                            {
                                "conditions": [
                                    {
                                        "bundle_identifiers": [
                                            "^com\\.apple\\.Terminal$",
                                            "^com\\.googlecode\\.iterm2$",
                                            "^co\\.zeit\\.hyperterm$",
                                            "^co\\.zeit\\.hyper$",
                                            "^io\\.alacritty$",
                                            "^org\\.alacritty$",
                                            "^net\\.kovidgoyal\\.kitty$",
                                            "^com\\.microsoft\\.VSCode$"
                                        ],
                                        "type": "frontmost_application_unless"
                                    }
                                ],
                                "from": {
                                    "key_code": "w",
                                    "modifiers": {
                                        "mandatory": [
                                            "left_control"
                                        ]
                                    }
                                },
                                "to": [
                                    {
                                        "key_code": "delete_or_backspace",
                                        "modifiers": [
                                            "option"
                                        ]
                                    }
                                ],
                                "type": "basic"
                            },
                            {
                                "from": {
                                    "key_code": "d",
                                    "modifiers": {
                                        "mandatory": [
                                            "left_control"
                                        ]
                                    }
                                },
                                "to": [
                                    {
                                        "key_code": "delete_or_backspace"
                                    }
                                ],
                                "type": "basic"
                            },
                            {
                                "conditions": [
                                    {
                                        "bundle_identifiers": [
                                            "^com\\.apple\\.Terminal$",
                                            "^com\\.googlecode\\.iterm2$",
                                            "^co\\.zeit\\.hyperterm$",
                                            "^co\\.zeit\\.hyper$",
                                            "^io\\.alacritty$",
                                            "^org\\.alacritty$",
                                            "^net\\.kovidgoyal\\.kitty$",
                                            "^com\\.microsoft\\.VSCode$"
                                        ],
                                        "type": "frontmost_application_unless"
                                    }
                                ],
                                "from": {
                                    "key_code": "u",
                                    "modifiers": {
                                        "mandatory": [
                                            "left_control"
                                        ]
                                    }
                                },
                                "to": [
                                    {
                                        "key_code": "left_arrow",
                                        "modifiers": [
                                            "command",
                                            "shift"
                                        ]
                                    },
                                    {
                                        "key_code": "delete_or_backspace"
                                    }
                                ],
                                "type": "basic"
                            },
                            {
                                "conditions": [
                                    {
                                        "bundle_identifiers": [
                                            "^com\\.apple\\.Terminal$",
                                            "^com\\.googlecode\\.iterm2$",
                                            "^co\\.zeit\\.hyperterm$",
                                            "^co\\.zeit\\.hyper$",
                                            "^io\\.alacritty$",
                                            "^org\\.alacritty$",
                                            "^net\\.kovidgoyal\\.kitty$",
                                            "^com\\.microsoft\\.VSCode$"
                                        ],
                                        "type": "frontmost_application_unless"
                                    }
                                ],
                                "from": {
                                    "key_code": "v",
                                    "modifiers": {
                                        "mandatory": [
                                            "left_control"
                                        ]
                                    }
                                },
                                "to": [
                                    {
                                        "key_code": "left_arrow",
                                        "modifiers": [
                                            "option",
                                            "shift"
                                        ]
                                    }
                                ],
                                "type": "basic"
                            }
                        ]
                    },
                    {
                        "description": "CapsLock → Control (hold) / Esc (tap)",
                        "manipulators": [
                            {
                                "description": "Change caps_lock to control",
                                "from": {
                                    "key_code": "caps_lock",
                                    "modifiers": {
                                        "optional": [
                                            "any"
                                        ]
                                    }
                                },
                                "to": [
                                    {
                                        "key_code": "left_control"
                                    }
                                ],
                                "to_if_alone": [
                                    {
                                        "key_code": "escape"
                                    }
                                ],
                                "type": "basic"
                            }
                        ]
                    }
                ]
            },
            "devices": [
                {
                    "identifiers": {
                        "is_keyboard": true,
                        "product_id": 73,
                        "vendor_id": 9610
                    },
                    "simple_modifications": [
                        {
                            "from": {
                                "key_code": "left_command"
                            },
                            "to": [
                                {
                                    "key_code": "left_option"
                                }
                            ]
                        },
                        {
                            "from": {
                                "key_code": "left_option"
                            },
                            "to": [
                                {
                                    "key_code": "left_command"
                                }
                            ]
                        }
                    ]
                }
            ],
            "name": "Normies",
            "virtual_hid_keyboard": {
                "keyboard_type_v2": "iso"
            }
        }
    ]
}